common_test_ceair/__init__.py
common_test_ceair/study_1.py
common_test_ceair-0.0.3.1.dist-info/METADATA
common_test_ceair-0.0.3.1.dist-info/WHEEL
common_test_ceair-0.0.3.1.dist-info/top_level.txt
common_test_ceair-0.0.3.1.dist-info/RECORD
