Metadata-Version: 2.1
Name: common_test_ceair
Version: 0.0.3.1
Requires-Dist: requests
